signalr_aio/__init__.py
signalr_aio/_connection.py
signalr_aio/events/__init__.py
signalr_aio/events/_events.py
signalr_aio/hubs/__init__.py
signalr_aio/hubs/_hub.py
signalr_aio/transports/__init__.py
signalr_aio/transports/_exceptions.py
signalr_aio/transports/_parameters.py
signalr_aio/transports/_queue_events.py
signalr_aio/transports/_transport.py
py_signalr_client-0.0.2.dist-info/LICENSE
py_signalr_client-0.0.2.dist-info/METADATA
py_signalr_client-0.0.2.dist-info/WHEEL
py_signalr_client-0.0.2.dist-info/top_level.txt
py_signalr_client-0.0.2.dist-info/RECORD
