Metadata-Version: 2.1
Name: py-signalr-client
Version: 0.0.2
Summary: Simple python SignalR client using asyncio.
Home-page: https://github.com/srijanshetty/py-signalr-client
Download-URL: https://github.com/srijanshetty/py-signalr-client.git
Author: Srijan R Shetty
Author-email: srs@srijanshetty.in
License: MIT
Keywords: signalr,sginalr-weboscket,signalr-client,signalr-asyncio,signalr-aio
Platform: UNKNOWN
License-File: LICENSE
Requires-Dist: requests (>=2.18.4)
Requires-Dist: websockets (>=4.0.1)
